miya_speechless/__init__.py
miya_speechless/globals.py
miya_speechless/audio/__init__.py
miya_speechless/audio/audio_quality.py
miya_speechless/audio/convert_audio.py
miya_speechless/audio/io.py
miya_speechless/audio/preprocessing.py
miya_speechless/audio/speaker_diarization.py
miya_speechless/models/__init__.py
miya_speechless/models/llm_client.py
miya_speechless/models/onnx.py
miya_speechless/nlp/__init__.py
miya_speechless/nlp/language.py
miya_speechless/nlp/loader.py
miya_speechless/nlp/prompt.py
miya_speechless/nlp/sentiment_analysis.py
miya_speechless/prompts/sentiment_score.j2
miya_speechless/prompts/summarize.j2
miya_speechless/prompts/tags.j2
miya_speechless/transcribe/__init__.py
miya_speechless/transcribe/base.py
miya_speechless/transcribe/clients.py
miya_speechless-0.0.28.dist-info/METADATA
miya_speechless-0.0.28.dist-info/WHEEL
miya_speechless-0.0.28.dist-info/RECORD
