Metadata-Version: 2.4
Name: miya-speechless
Version: 0.0.28
Summary: Speechless repo for sales call analysis
Author: Michal Pleva (MIYA Consulting), Niek Mereu (MIYA Consulting)
License-Expression: MIT
Requires-Python: <3.11,>=3.10
Requires-Dist: ctc-forced-aligner>=1.0.2
Requires-Dist: deepmultilingualpunctuation>=1.0.1
Requires-Dist: elevenlabs<3,>=2.3.0
Requires-Dist: faster-whisper>=1.2.0
Requires-Dist: google-cloud-speech<3,>=2.33.0
Requires-Dist: librosa<0.12,>=0.11.0
Requires-Dist: litellm<2,>=1.72.2
Requires-Dist: nemo-toolkit[asr]
Requires-Dist: nltk>=3.9.1
Requires-Dist: noisereduce<4,>=3.0.3
Requires-Dist: numba<0.62,>=0.61
Requires-Dist: onnx<2,>=1.17.0
Requires-Dist: onnxruntime<2,>=1.20.0
Requires-Dist: openai<2,>=1.51.2
Requires-Dist: pvfalcon<2,>=1.0.2
Requires-Dist: pyannote-audio<4,>=3.3.2
Requires-Dist: pydantic<3,>=2.11.7
Requires-Dist: pydub<0.26,>=0.25.1
Requires-Dist: python-dotenv<2,>=1.0.1
Requires-Dist: pytubefix<8,>=7.4.0
Requires-Dist: silero-vad<6,>=5.1.2
Requires-Dist: streamlit-advanced-audio<0.2,>=0.1.1
Requires-Dist: streamlit-audiorec<0.2,>=0.1.3
Requires-Dist: streamlit-webrtc<0.61,>=0.60.2
Requires-Dist: streamlit~=1.44
Requires-Dist: tiktoken<0.9,>=0.8.0
Requires-Dist: twine<6,>=5.1.1
Requires-Dist: websockets<16,>=15.0.1
Requires-Dist: wget>=3.2
